gym_sphero/__init__.py
gym_sphero/envs/__init__.py
gym_sphero/envs/sphero_env.py
gym_sphero-0.0.7.dist-info/METADATA
gym_sphero-0.0.7.dist-info/WHEEL
gym_sphero-0.0.7.dist-info/top_level.txt
gym_sphero-0.0.7.dist-info/RECORD
