Metadata-Version: 2.1
Name: gym-sphero
Version: 0.0.7
Summary: UNKNOWN
Home-page: UNKNOWN
Author: UNKNOWN
Author-email: UNKNOWN
License: UNKNOWN
Platform: UNKNOWN
Requires-Dist: gym
Requires-Dist: numpy
Requires-Dist: spheropy (>=0.0.4)
